dff.v
module DFF (
	input wire clk,
	input wire reset,
	input wire d,
	output reg q
	);

	always @(posedge clk) begin
		if(reset == 1'b1) q <= 0;
		else q <= d;
	end
endmodule

instdecoder.v
// XOR 00
// OUT 01
// SETL 10
// SETR 11

module ISXOR (
	input wire[1:0] inst,
	output wire judge
	);
	assign judge = (!inst[0] & !inst[1]);
endmodule

module ISOUT (
	input wire[1:0] inst,
	output wire judge
	);
	assign judge = (inst[0] & !inst[1]);
endmodule

module ISSETL (
	input wire[1:0] inst,
	output wire judge
	);
	assign judge = (!inst[0] & inst[1]);
endmodule

module ISSETR (
	input wire[1:0] inst,
	output wire judge
	);
	assign judge = (inst[0] & inst[1]);
endmodule

endpreg.v
module ENDPREG (
	input wire clk,
	input wire reset,
	input wire[1:0] inst,
	input wire ztonxor,
	output wire ltorxor
	);

	wire isSETL, isSETR;
	ISSETL setljudge(inst, isSETL);
	ISSETR setrjudge(inst, isSETR);
	wire delayed_clk;
	assign #1 delayed_clk = clk;

	wire dL, qL;
	assign dL = (isSETL&ztonxor) | (!isSETL&qL);
	DFF regL(delayed_clk, reset, dL, qL);

	wire dR, qR;
	assign dR = (isSETR&ztonxor) | (!isSETR&qR);
	DFF regR(delayed_clk, reset, dR, qR);

	assign ltorxor = qL ^ qR;
endmodule

tests/endpreg_test.v
module ENDPREGTEST;

reg clk, reset, ztonxor;
reg[1:0] inst = 2'b00;
wire ltorxor;

parameter STEP = 10;
always begin
	clk = 1; #(STEP/2);
	clk = 0; #(STEP/2);
end

ENDPREG endpreg(clk, reset, inst, ztonxor, ltorxor);

initial begin
	$dumpfile("endpreg_test.vcd");
	$dumpvars(1, ENDPREGTEST);
		reset = 1'b1;
	#STEP	reset = 1'b0;
	#STEP	inst = 2'b10; ztonxor = 1'b1;
	#STEP	inst = 2'b00; ztonxor = 1'b1;
	#STEP	inst = 2'b11; ztonxor = 1'b1;
	#STEP	inst = 2'b10; ztonxor = 1'b1;
	#STEP	inst = 2'b10; ztonxor = 1'b0;
	#STEP	$finish;
end

endmodule

endpreg_test.vcd
$date
	Sun Jan 23 15:55:18 2022
$end
$version
	Icarus Verilog
$end
$timescale
	1s
$end
$scope module ENDPREGTEST $end
$var wire 1 ! ltorxor $end
$var reg 1 " clk $end
$var reg 2 # inst [1:0] $end
$var reg 1 $ reset $end
$var reg 1 % ztonxor $end
$upscope $end
$enddefinitions $end
#0
$dumpvars
x%
1$
b0 #
1"
0!
$end
#5
0"
#10
1"
0$
#15
0"
#20
1"
1%
b10 #
#21
1!
#25
0"
#30
1"
b0 #
#35
0"
#40
1"
b11 #
#41
0!
#45
0"
#50
1"
b10 #
#55
0"
#60
1"
0%
#61
1!
