dff.v
module DFF (
	input wire clk,
	input wire reset,
	input wire d,
	output reg q
	);

	always @(posedge clk) begin
		if(reset == 1'b1) q <= 0;
		else q <= d;
	end
endmodule

reg.v
module REGCORE (
        input wire clk,
        input wire reset,
        input wire in0,
        input wire in_use,
        input wire out_use,
        output wire out0
        );

        wire d, q;
        assign d = (in0 & in_use) ^ q;
        DFF bitreg(.clk(clk), .reset(reset), .d(d), .q(q));

        assign out0 = q & out_use;
endmodule


module REG1B8SZ (
	input wire clk,
	input wire reset,
	input wire[1:0] inst,
	input wire[2:0] idx,
	input wire xorval,
	output wire rangexor,
	output wire delayed_clk
	//output wire[7:0] dat, DEBUG WIRE
	//output wire[7:0] bd
	);

	wire[2:0] in_idx, out_idx;
	generate
		genvar i;
		for(i=0; i<3; i=i+1) begin
			assign in_idx[i] = idx[i] | (inst[0] | inst[1]);
			assign out_idx[i] = idx[i];
		end
	endgenerate
	
	wire[7:0] in_use, out_use;
	INDECODER8 indec(in_idx, in_use);
	OUTDECODER8 outdec(out_idx, out_use);
	
        assign #1 delayed_clk = clk;
	wire[7:0] bd;
	REGCORE regcore0(delayed_clk, reset, xorval, in_use[0], out_use[0], bd[0]);
	REGCORE regcore1(delayed_clk, reset, xorval, in_use[1], out_use[1], bd[1]);
	REGCORE regcore2(delayed_clk, reset, xorval, in_use[2], out_use[2], bd[2]);
	REGCORE regcore3(delayed_clk, reset, xorval, in_use[3], out_use[3], bd[3]);
	REGCORE regcore4(delayed_clk, reset, xorval, in_use[4], out_use[4], bd[4]);
	REGCORE regcore5(delayed_clk, reset, xorval, in_use[5], out_use[5], bd[5]);
	REGCORE regcore6(delayed_clk, reset, xorval, in_use[6], out_use[6], bd[6]);
	REGCORE regcore7(delayed_clk, reset, xorval, in_use[7], out_use[7], bd[7]);

	assign rangexor = bd[0] ^ bd[1] ^ bd[2] ^ bd[3] ^ bd[4] ^ bd[5] ^ bd[6] ^ bd[7];
endmodule

regdecoder.v
module INDECODER2STEP (
	input wire idx,
	input wire p,
	output wire[1:0] mask
	);

	assign mask[0] = p & !idx;
	assign mask[1] = p | idx;
endmodule


module INDECODER4STEP (
	input wire idx,
	input wire[1:0] p,
	output wire[3:0] mask
	);

	assign mask[0] = p[0] & !idx;
	assign mask[1] = p[1] & !idx;
	assign mask[2] = p[0] & idx;
	assign mask[3] = p[1] | idx;
endmodule


module INDECODER8STEP (
	input wire idx,
	input wire[3:0] p,
	output wire[7:0] mask
	);
	
	generate
		genvar i;
		for(i=0; i<4; i=i+1) assign mask[i] = p[i] & !idx;
		for(i=4; i<7; i=i+1) assign mask[i] = p[i-4] & idx;
		assign mask[7] = p[3] | idx;
	endgenerate

endmodule


module INDECODER8 (
	input wire[2:0] idx,
	output wire[7:0] mask
	);

	reg src = 1'b1;
	wire[1:0] p2b;
	INDECODER2STEP bit0(idx[0], src, p2b);
	wire[3:0] p4b;
	INDECODER4STEP bit1(idx[1], p2b, p4b);
	INDECODER8STEP bit2(idx[2], p4b, mask);
endmodule


// -------------------------------------------


module OUTDECODER2STEP (
	input wire idx,
	input wire p,
	output wire[1:0] mask
	);

	assign mask[0] = p | idx;
	assign mask[1] = p & idx;
endmodule


module OUTDECODER4STEP (
	input wire idx,
	input wire[1:0] p,
	output wire[3:0] mask
	);

	assign mask[0] = p[0] & !idx;
	assign mask[1] = p[1] | idx;
	assign mask[2] = p[0] & idx;
	assign mask[3] = p[1] & idx;
endmodule


module OUTDECODER8STEP (
	input wire idx,
	input wire[3:0] p,
	output wire[7:0] mask
	);

	generate
		genvar i;
		for(i=0; i<3; i=i+1) assign mask[i] = p[i] & !idx;
		assign mask[3] = p[3] | idx;
		for(i=4; i<8; i=i+1) assign mask[i] = p[i-4] & idx;
	endgenerate

endmodule


module OUTDECODER8 (
	input wire[2:0] idx,
	output wire[7:0] mask
	);

	reg gnd = 1'b0;	
	wire[1:0] p2b;
	OUTDECODER2STEP bit0(idx[0], gnd, p2b);
	wire[3:0] p4b;
	OUTDECODER4STEP bit1(idx[1], p2b, p4b);
	OUTDECODER8STEP bit2(idx[2], p4b, mask);
endmodule

tests/reg_test.v
module REGTEST;

reg clk, reset;
reg[1:0] inst;		// 00=xor idx val, 01=setr idx
reg[2:0] idx = 3'b000;
reg in0 = 0;
wire rangexor;

parameter STEP = 10;
always begin
	clk = 1; #(STEP/2);
	clk = 0; #(STEP/2);
end


wire[7:0] dat;
wire[7:0] out_use;
wire[7:0] bd;
wire delayed_clk;
REG1B8SZ xreg(clk, reset, inst, idx, in0, out0, delayed_clk);

initial begin
	$dumpfile("reg_test.vcd");
	$dumpvars(1, REGTEST);
	#STEP	reset = 1'b1;
	#STEP	reset = 1'b0;
	#STEP	inst = 2'b00; in0 = 1'b1; idx = 3'b000;
	#STEP	inst = 2'b00; in0 = 1'b0; idx = 3'b000;
	#STEP	inst = 2'b00; in0 = 1'b1; idx = 3'b100;
	#STEP	inst = 2'b10; in0 = 1'b0; idx = 3'b111;
	#STEP	inst = 2'b10; in0 = 1'b0; idx = 3'b011;
	#STEP	inst = 2'b10; in0 = 1'b1; idx = 3'b100;

	#STEP	inst = 2'b00; in0 = 1'b1; idx = 3'b101;
	#STEP	inst = 2'b00; in0 = 1'b1; idx = 3'b110;
	#STEP	inst = 2'b00; in0 = 1'b1; idx = 3'b000;
	#STEP	inst = 2'b10; in0 = 1'b0; idx = 3'b011;
	#STEP	inst = 2'b10; in0 = 1'b1; idx = 3'b111;
	#STEP	$finish;	
end

endmodule

reg_test.vcd
$date
	Sun Jan 23 15:28:10 2022
$end
$version
	Icarus Verilog
$end
$timescale
	1s
$end
$scope module REGTEST $end
$var wire 1 ! out0 $end
$var wire 1 " delayed_clk $end
$var reg 1 # clk $end
$var reg 3 $ idx [2:0] $end
$var reg 1 % in0 $end
$var reg 2 & inst [1:0] $end
$var reg 1 ' reset $end
$upscope $end
$enddefinitions $end
#0
$dumpvars
x'
bx &
0%
b0 $
1#
x"
0!
$end
#1
1"
#5
0#
#6
0"
#10
1#
1'
#11
1"
#15
0#
#16
0"
#20
1#
0'
#21
1"
#25
0#
#26
0"
#30
1#
1%
b0 &
#31
1"
#35
0#
#36
0"
#40
1#
0%
#41
1"
#45
0#
#46
0"
#50
1!
1#
b100 $
1%
#51
1"
#55
0#
#56
0"
#60
0!
1#
b111 $
0%
b1 &
#61
1"
#65
0#
#66
0"
#70
1!
1#
b11 $
#71
1"
#75
0#
#76
0"
#80
1!
1#
b100 $
1%
#81
1"
#85
0#
#86
0"
#90
0!
1#
b101 $
b0 &
#91
1"
#95
0#
#96
0"
#100
1!
1#
b110 $
#101
1"
#105
0#
#106
0"
#110
0!
1#
b0 $
#111
1"
#115
0#
#116
0"
#120
1#
b11 $
0%
b1 &
#121
1"
#125
0#
#126
0"
#130
1!
1#
b111 $
1%
